setup.cfg
setup.py
skeletool/__init__.py
skeletool/container.py
skeletool/controller.py
skeletool/help.py
skeletool/options.py
skeletool/skeletool.py
skeletool.egg-info/PKG-INFO
skeletool.egg-info/SOURCES.txt
skeletool.egg-info/dependency_links.txt
skeletool.egg-info/entry_points.txt
skeletool.egg-info/top_level.txt