Metadata-Version: 1.0
Name: skeletool
Version: 0.3dev
Summary: Framework package for integrated command-line development
Home-page: UNKNOWN
Author: Fabien Bouleau
Author-email: fabien.bouleau@gmail.com
License: GPLv3
Keywords: framework command-line API
Platform: UNKNOWN
